afscgap/README.md
afscgap/__init__.py
afscgap/convert.py
afscgap/cursor.py
afscgap/flat.py
afscgap/flat_cursor.py
afscgap/flat_http.py
afscgap/flat_index_util.py
afscgap/flat_local_filter.py
afscgap/flat_model.py
afscgap/http_util.py
afscgap/model.py
afscgap/model_util.py
afscgap/param.py
afscgap/py.typed
afscgap/typesdef.py
afscgap-2.0.1.dist-info/METADATA
afscgap-2.0.1.dist-info/WHEEL
afscgap-2.0.1.dist-info/licenses/LICENSE.md
afscgap-2.0.1.dist-info/RECORD
