Metadata-Version: 2.4
Name: afscgap
Version: 2.0.1
Summary: Tools for interacting with the public bottom trawl surveys data from the NOAA AFSC GAP.
Project-URL: Homepage, https://pyafscgap.org
Project-URL: Documentation, https://pyafscgap.org/devdocs/afscgap.html
Project-URL: Source, https://github.com/SchmidtDSE/afscgap
Project-URL: Issue Tracker, https://github.com/SchmidtDSE/afscgap/issues
Project-URL: Changelog, https://github.com/SchmidtDSE/afscgap#version-history
Author-email: A Samuel Pottinger <sam.pottinger@berkeley.edu>
License-File: LICENSE.md
Classifier: Development Status :: 5 - Production/Stable
Classifier: Intended Audience :: Developers
Classifier: Intended Audience :: Science/Research
Classifier: License :: OSI Approved :: BSD License
Classifier: Operating System :: OS Independent
Classifier: Programming Language :: Python :: 3
Classifier: Topic :: Scientific/Engineering
Classifier: Topic :: Software Development :: Libraries
Requires-Python: >=3.7
Requires-Dist: fastavro~=1.9.7
Requires-Dist: requests~=2.32.3
Provides-Extra: dev
Requires-Dist: build; extra == 'dev'
Requires-Dist: mkdocs; extra == 'dev'
Requires-Dist: mkdocs-windmill; extra == 'dev'
Requires-Dist: mypy; extra == 'dev'
Requires-Dist: nose2; extra == 'dev'
Requires-Dist: pdoc; extra == 'dev'
Requires-Dist: pycodestyle; extra == 'dev'
Requires-Dist: pyflakes; extra == 'dev'
Requires-Dist: twine; extra == 'dev'
Requires-Dist: types-requests; extra == 'dev'
